aliyunsdkcodeup/__init__.py
aliyunsdkcodeup/request/__init__.py
aliyunsdkcodeup/request/v20200414/AcceptMergeRequestRequest.py
aliyunsdkcodeup/request/v20200414/AddGroupMemberRequest.py
aliyunsdkcodeup/request/v20200414/AddRepositoryMemberRequest.py
aliyunsdkcodeup/request/v20200414/AddWebhookRequest.py
aliyunsdkcodeup/request/v20200414/CreateBranchRequest.py
aliyunsdkcodeup/request/v20200414/CreateFileRequest.py
aliyunsdkcodeup/request/v20200414/CreateMergeRequestCommentRequest.py
aliyunsdkcodeup/request/v20200414/CreateMergeRequestRequest.py
aliyunsdkcodeup/request/v20200414/CreateRepositoryDeployKeyRequest.py
aliyunsdkcodeup/request/v20200414/CreateRepositoryGroupRequest.py
aliyunsdkcodeup/request/v20200414/CreateRepositoryProtectedBranchRequest.py
aliyunsdkcodeup/request/v20200414/CreateRepositoryRequest.py
aliyunsdkcodeup/request/v20200414/CreateSshKeyRequest.py
aliyunsdkcodeup/request/v20200414/CreateTagRequest.py
aliyunsdkcodeup/request/v20200414/DeleteBranchRequest.py
aliyunsdkcodeup/request/v20200414/DeleteFileRequest.py
aliyunsdkcodeup/request/v20200414/DeleteGroupMemberRequest.py
aliyunsdkcodeup/request/v20200414/DeleteRepositoryGroupRequest.py
aliyunsdkcodeup/request/v20200414/DeleteRepositoryMemberRequest.py
aliyunsdkcodeup/request/v20200414/DeleteRepositoryProtectedBranchRequest.py
aliyunsdkcodeup/request/v20200414/DeleteRepositoryRequest.py
aliyunsdkcodeup/request/v20200414/DeleteRepositoryTagRequest.py
aliyunsdkcodeup/request/v20200414/DeleteRepositoryTagV2Request.py
aliyunsdkcodeup/request/v20200414/DeleteRepositoryWebhookRequest.py
aliyunsdkcodeup/request/v20200414/EnableRepositoryDeployKeyRequest.py
aliyunsdkcodeup/request/v20200414/GetBranchInfoRequest.py
aliyunsdkcodeup/request/v20200414/GetCodeCompletionRequest.py
aliyunsdkcodeup/request/v20200414/GetCodeupOrganizationRequest.py
aliyunsdkcodeup/request/v20200414/GetFileBlobsRequest.py
aliyunsdkcodeup/request/v20200414/GetGroupDetailRequest.py
aliyun_python_sdk_codeup-0.1.3.dist-info/LICENSE
aliyun_python_sdk_codeup-0.1.3.dist-info/METADATA
aliyun_python_sdk_codeup-0.1.3.dist-info/WHEEL
aliyun_python_sdk_codeup-0.1.3.dist-info/top_level.txt
aliyun_python_sdk_codeup-0.1.3.dist-info/RECORD
